apimaticswaggerpetstore/__init__.py
apimaticswaggerpetstore/api_helper.py
apimaticswaggerpetstore/apimaticswaggerpetstore_client.py
apimaticswaggerpetstore/configuration.py
apimaticswaggerpetstore/decorators.py
apimaticswaggerpetstore/controllers/__init__.py
apimaticswaggerpetstore/controllers/base_controller.py
apimaticswaggerpetstore/controllers/pet_controller.py
apimaticswaggerpetstore/controllers/store_controller.py
apimaticswaggerpetstore/controllers/user_controller.py
apimaticswaggerpetstore/exceptions/__init__.py
apimaticswaggerpetstore/exceptions/api_exception.py
apimaticswaggerpetstore/http/__init__.py
apimaticswaggerpetstore/http/http_call_back.py
apimaticswaggerpetstore/http/http_client.py
apimaticswaggerpetstore/http/http_context.py
apimaticswaggerpetstore/http/http_method_enum.py
apimaticswaggerpetstore/http/http_request.py
apimaticswaggerpetstore/http/http_response.py
apimaticswaggerpetstore/http/requests_client.py
apimaticswaggerpetstore/models/__init__.py
apimaticswaggerpetstore/models/api_response.py
apimaticswaggerpetstore/models/category.py
apimaticswaggerpetstore/models/o_auth_scope_enum.py
apimaticswaggerpetstore/models/order.py
apimaticswaggerpetstore/models/pet.py
apimaticswaggerpetstore/models/status_1_enum.py
apimaticswaggerpetstore/models/status_2_enum.py
apimaticswaggerpetstore/models/status_enum.py
apimaticswaggerpetstore/models/tag.py
apimaticswaggerpetstore/models/user.py
apimaticswaggerpetstore-1.0.0.dist-info/LICENSE
apimaticswaggerpetstore-1.0.0.dist-info/METADATA
apimaticswaggerpetstore-1.0.0.dist-info/WHEEL
apimaticswaggerpetstore-1.0.0.dist-info/top_level.txt
apimaticswaggerpetstore-1.0.0.dist-info/RECORD
