Metadata-Version: 2.1
Name: apimaticswaggerpetstore
Version: 1.0.0
Summary: Python client library for Swagger Petstore API
Home-page: https://apimatic.io
Author: APIMatic SDK Generator
Author-email: apiteam@swagger.io
License: UNKNOWN
Platform: UNKNOWN
Requires-Dist: requests (<3.0,>=2.9.1)
Requires-Dist: jsonpickle (<1.0,>=0.7.1)
Requires-Dist: cachecontrol (<1.0,>=0.11.7)
Requires-Dist: python-dateutil (<3.0,>=2.5.3)
